clria/__init__.py
clria/plotting/__init__.py
clria/plotting/_plotting.py
clria/preprocessing/__init__.py
clria/preprocessing/_bncm.py
clria/preprocessing/_lr.py
clria/preprocessing/LRdatabase/lrdb_cell.tsv
clria/preprocessing/LRdatabase/lrdb_neuron.tsv
clria/simulate/__init__.py
clria/simulate/_iot.py
clria/tools/__init__.py
clria/tools/_mmot.py
clria/tools/_spin.py
clria/tools/_tca.py
clria/tools/_uotr.py
clria-1.0.9.dist-info/LICENSE
clria-1.0.9.dist-info/METADATA
clria-1.0.9.dist-info/WHEEL
clria-1.0.9.dist-info/top_level.txt
clria-1.0.9.dist-info/RECORD
