Metadata-Version: 2.1
Name: clria
Version: 1.0.9
Summary: Package to decipher LRI-mediated brain network communication
Home-page: https://github.com/duzc-Repos/CLRIA
Author: DU Zongchang
License: MIT
Classifier: Intended Audience :: Science/Research
Classifier: License :: OSI Approved :: MIT License
Classifier: Programming Language :: Python :: 3.8
Requires-Python: >=3.8
License-File: LICENSE
Requires-Dist: numpy
Requires-Dist: pandas
Requires-Dist: tensorly
Requires-Dist: fastparquet
Requires-Dist: scipy
Requires-Dist: statsmodels
Requires-Dist: scikit-learn
Requires-Dist: nibabel
Requires-Dist: netneurotools
Requires-Dist: bctpy
Requires-Dist: POT
Requires-Dist: seaborn
Requires-Dist: plotnine
Requires-Dist: plotly
Requires-Dist: pycirclize
Requires-Dist: kaleido
Requires-Dist: nbformat
Requires-Dist: tqdm
